pyincert/__init__.py
pyincert/core.py
pyincert/math.py
pyincert/math_core.py
pyincert/util.py
pyincert-1.0.0.dist-info/LICENSE
pyincert-1.0.0.dist-info/METADATA
pyincert-1.0.0.dist-info/WHEEL
pyincert-1.0.0.dist-info/top_level.txt
pyincert-1.0.0.dist-info/RECORD
